BBSpider/BBSP.py
BBSpider/__init__.py
BBSpider-0.2.8.dist-info/LICENSE
BBSpider-0.2.8.dist-info/METADATA
BBSpider-0.2.8.dist-info/WHEEL
BBSpider-0.2.8.dist-info/top_level.txt
BBSpider-0.2.8.dist-info/RECORD
