Metadata-Version: 2.1
Name: BBSpider
Version: 0.2.8
Summary: a web spider
Home-page: https://www.dailyrecords.xyz/
Author: ZzxxH
Author-email: 654245529@qq.com
License: UNKNOWN
Project-URL: Bug Tracker, https://www.dailyrecords.xyz/
Platform: UNKNOWN
Classifier: Programming Language :: Python :: 3
Classifier: License :: OSI Approved :: MIT License
Classifier: Operating System :: OS Independent
Requires-Python: >=3.6
License-File: LICENSE
Requires-Dist: pandas
Requires-Dist: bs4
Requires-Dist: requests
Requires-Dist: jieba
Requires-Dist: pyecharts
